pandastools/__init__.py
pandastools/accessors/__init__.py
pandastools/accessors/dataframe.py
pandastools/accessors/index.py
pandastools/accessors/scipydataframe.py
pandastools/accessors/series.py
pandastools/dtypes.py
pandastools/py.typed
pandastools/utils/__init__.py
pandastools/utils/dataimport.py
pandastools/utils/helpers.py
pandastools-0.7.0.dist-info/LICENSE
pandastools-0.7.0.dist-info/METADATA
pandastools-0.7.0.dist-info/WHEEL
pandastools-0.7.0.dist-info/RECORD
