Metadata-Version: 2.1
Name: pandastools
Version: 0.7.0
Summary: Helper functions for Pandas DataFrames / Series
Home-page: https://github.com/phil65/pandastools
Author: phil65
Author-email: philipptemminghoff@googlemail.com
Requires-Python: >=3.10,<3.12
Classifier: Programming Language :: Python :: 3
Classifier: Programming Language :: Python :: 3.10
Classifier: Programming Language :: Python :: 3.11
Provides-Extra: addons
Requires-Dist: bidict (>=0,<1)
Requires-Dist: pandas
Requires-Dist: scipy (>=1.7,<2.0) ; (python_version >= "3.10" and python_version < "3.12") and (extra == "addons")
Project-URL: Repository, https://github.com/phil65/pandastools
